#########################################################################################
<poster>Pinky</poster>
<thumbnail></thumbnail>
<fanart></fanart>
#########################################################################################

<dir>
<name>Movies 2017</name>
<link>https://raw.githubusercontent.com/jmartinez80/first/master/movies2017.xml</link>
<thumbnail></thumbnail>
<summary>My Personal Faves Movies</summary>
</dir>

<dir>
<name>Movies 2016</name>
<link>https://raw.githubusercontent.com/jmartinez80/first/master/movies2016.xml</link>
<thumbnail></thumbnail>
<summary>My Personal Faves Movies</summary>
</dir>

<dir>
<name>Movies 2015</name>
<link>https://raw.githubusercontent.com/jmartinez80/first/master/movies2015.xml</link>
<thumbnail></thumbnail>
<summary>My Personal Faves Movies</summary>
</dir>

<dir>
<name>Older Movies</name>
<link>https://raw.githubusercontent.com/jmartinez80/first/master/oldermovies.xml</link>
<thumbnail></thumbnail>
<summary>My Personal Faves Movies</summary>
</dir>

<dir>
<name>Animated</name>
<link>https://raw.githubusercontent.com/jmartinez80/first/master/animatedMovies.xml</link>
<thumbnail></thumbnail>
<summary>My Personal Faves Movies</summary>
</dir>

<dir>
<title>Gangster Movies</title>
<tmdb>list/38640</tmdb>
<summary>A selection of Gangster Films</summary>
</dir>

<dir>
<title>Animated Movies</title>
<tmdb>list/ls020270696/</tmdb>
<summary>A selection of Gangster Films</summary>
</dir>



